MANIFEST.in
README.rst
setup.py
html_tree_diff.egg-info/PKG-INFO
html_tree_diff.egg-info/SOURCES.txt
html_tree_diff.egg-info/dependency_links.txt
html_tree_diff.egg-info/not-zip-safe
html_tree_diff.egg-info/requires.txt
html_tree_diff.egg-info/top_level.txt
htmltreediff/__init__.py
htmltreediff/changes.py
htmltreediff/cli.py
htmltreediff/diff_core.py
htmltreediff/edit_script_runner.py
htmltreediff/html.py
htmltreediff/test_html.py
htmltreediff/test_main.py
htmltreediff/test_text.py
htmltreediff/test_util.py
htmltreediff/test_xml.py
htmltreediff/tests.py
htmltreediff/text.py
htmltreediff/util.py