Metadata-Version: 1.0
Name: html-tree-diff
Version: 0.1.2
Summary: Structure-aware diff for html and xml documents
Home-page: http://github.com/christian-oudard/htmltreediff/
Author: Christian Oudard
Author-email: christian.oudard@gmail.com
License: BSD
Platform: any
Classifier: Development Status :: 3 - Alpha
Classifier: Programming Language :: Python
Classifier: Intended Audience :: Developers
Classifier: License :: OSI Approved :: BSD License
Classifier: Operating System :: OS Independent
Classifier: Topic :: Text Processing :: Markup :: HTML
Classifier: Topic :: Text Processing :: Markup :: XML
